simple_perms/__init__.py
simple_perms/apps.py
simple_perms/backend.py
simple_perms/helpers.py
simple_perms/logic.py
simple_perms/registry.py
simple_perms/settings.py
django_simple_perms-1.2.0.dist-info/LICENSE
django_simple_perms-1.2.0.dist-info/METADATA
django_simple_perms-1.2.0.dist-info/WHEEL
django_simple_perms-1.2.0.dist-info/RECORD
